spladder/__init__.py
spladder/count.py
spladder/editgraph.py
spladder/hdf5.py
spladder/helpers.py
spladder/helpers_viz.py
spladder/init.py
spladder/merge.py
spladder/reads.py
spladder/settings.py
spladder/spladder.py
spladder/spladder_build.py
spladder/spladder_prep.py
spladder/spladder_test.py
spladder/spladder_viz.py
spladder/utils.py
spladder/alt_splice/__init__.py
spladder/alt_splice/analyze.py
spladder/alt_splice/collect.py
spladder/alt_splice/detect.py
spladder/alt_splice/events.py
spladder/alt_splice/quantify.py
spladder/alt_splice/verify.py
spladder/alt_splice/write.py
spladder/classes/__init__.py
spladder/classes/counts.py
spladder/classes/datatrack.py
spladder/classes/event.py
spladder/classes/gene.py
spladder/classes/region.py
spladder/classes/segmentgraph.py
spladder/classes/splicegraph.py
spladder/core/__init__.py
spladder/core/gen_graphs.py
spladder/core/spladdercore.py
spladder/testing/__init__.py
spladder/testing/likelihood.py
spladder/viz/__init__.py
spladder/viz/axes.py
spladder/viz/coverage.py
spladder/viz/diagnose.py
spladder/viz/genelets.py
spladder/viz/graph.py
spladder/viz/highlight.py
tests/__init__.py
tests/test_end_to_end.py
tests/templates/annotation_pos.gtf
tests/testcase_basic/data/annotation_neg.gtf
tests/testcase_basic/data/annotation_neg.gtf.pickle
tests/testcase_basic/data/annotation_pos.gtf
tests/testcase_basic/data/annotation_pos.gtf.pickle
tests/testcase_basic/data/expr_ts.txt
tests/testcase_basic/data/genome_neg.fa
tests/testcase_basic/data/genome_pos.fa
tests/testcase_basic/data/testcase_basic_1.fq
tests/testcase_basic/data/testcase_basic_2.fq
tests/testcase_basic/data/testcase_basic_3.fq
tests/testcase_basic/data/testcase_basic_4.fq
tests/testcase_basic/data/testcase_basic_5.fq
tests/testcase_basic/data/align/neg_1.bam
tests/testcase_basic/data/align/neg_1.bam.bai
tests/testcase_basic/data/align/neg_1.conf_3.filt.hdf5
tests/testcase_basic/data/align/neg_1.hdf5
tests/testcase_basic/data/align/neg_2.bam
spladder-3.1.1.dist-info/AUTHORS
spladder-3.1.1.dist-info/METADATA
spladder-3.1.1.dist-info/WHEEL
spladder-3.1.1.dist-info/entry_points.txt
spladder-3.1.1.dist-info/top_level.txt
spladder-3.1.1.dist-info/RECORD
