Metadata-Version: 2.1
Name: spladder
Version: 3.1.1
Summary: Tool for the detection and quantification of alternative splicing events from RNA-Seq data.
Home-page: https://github.com/ratschlab/spladder
Author: Andre Kahles
Author-email: andre.kahles@inf.ethz.ch
License: BSD license
Keywords: spladder
Platform: UNKNOWN
Classifier: Development Status :: 2 - Pre-Alpha
Classifier: Intended Audience :: Developers
Classifier: License :: OSI Approved :: BSD License
Classifier: Natural Language :: English
Classifier: Programming Language :: Python :: 3
Classifier: Programming Language :: Python :: 3.8
Requires-Dist: numpy (>=1.26)
Requires-Dist: numba (>=0.59.0)
Requires-Dist: matplotlib (>=3.7)
Requires-Dist: scipy (>=1.13)
Requires-Dist: intervaltree (>=3.0.0)
Requires-Dist: h5py (>=2.2)
Requires-Dist: pysam (>=0.22.0)
Requires-Dist: statsmodels (>=0.14.0)
